{    "gasGiants": [   {       "name" : "Jupiter",            "satellites": [                "Ganymede",                "Callisto",                "Io",                "Europa"            ],            "mass": 1.8986e+27        },        {       "name": "Saturn",            "satellites": [                "Mimas",                "Enceladus",                "Tethys",                "Dione"            ],            "mass": 5.683e+26        }    ],    "rockyPlanets": [        {       "name" : "Earth",            "satellites": [                "Moon"            ],            "mass": 5.972e+24        },        {"name" : "Mars",            "satellites": [                "Phobos",                "Deimos"            ],            "mass": 6.39e+23        }    ]}